README.rst
optional_import.py
setup.py
optional_import.egg-info/PKG-INFO
optional_import.egg-info/SOURCES.txt
optional_import.egg-info/dependency_links.txt
optional_import.egg-info/top_level.txt