Metadata-Version: 1.0
Name: optional-import
Version: 1.2
Summary: Import something if it exists.
Home-page: https://github.com/cardforcoin/optional_import
Author: Chris Martin
Author-email: ch.martin@gmail.com
License: MIT
Platform: UNKNOWN
